{
  "$schema": "https://json-structure.org/meta/core/v0/#",
  "$id": "https://raw.githubusercontent.com/api-evangelist/adobe-campaign/refs/heads/main/json-structure/adobe-campaign-classic-workflow-post-event-request-structure.json",
  "name": "WorkflowPostEventRequest",
  "description": "SOAP envelope containing a signal event to post to a workflow, including the workflow ID, signal activity name, and optional XML variables.",
  "type": "object",
  "properties": {
    "workflowId": {
      "type": "int32",
      "description": "Internal ID of the target workflow.",
      "example": 42
    },
    "activity": {
      "type": "string",
      "description": "Name of the external signal activity in the workflow.",
      "example": "example_value"
    },
    "variables": {
      "type": "object",
      "description": "XML element containing variable parameters to pass to the workflow transition.",
      "additionalProperties": true
    }
  }
}